Metadata-Version: 2.1
Name: django-html-render
Version: 1.0.0
Summary: django html render
Home-page: https://github.com/reimibeta/django_html_render
Author: ReimiBeta
Author-email: reimi846@gmail.com
License: MIT
